abra/__init__.py
abra/config.py
abra/dataset.py
abra/experiment.py
abra/hypothesis_test.py
abra/mixin.py
abra/stats.py
abra/utils.py
abra/vis.py
abra/inference/__init__.py
abra/inference/inference_base.py
abra/inference/bayesian/__init__.py
abra/inference/bayesian/delta.py
abra/inference/bayesian/results.py
abra/inference/bayesian/models/__init__.py
abra/inference/bayesian/models/binary.py
abra/inference/bayesian/models/continuous.py
abra/inference/bayesian/models/counts.py
abra/inference/frequentist/__init__.py
abra/inference/frequentist/bootstrap.py
abra/inference/frequentist/means.py
abra/inference/frequentist/proportions.py
abra/inference/frequentist/rates.py
abra/inference/frequentist/results.py
abracadabra-0.0.7.dist-info/LICENSE
abracadabra-0.0.7.dist-info/METADATA
abracadabra-0.0.7.dist-info/WHEEL
abracadabra-0.0.7.dist-info/top_level.txt
abracadabra-0.0.7.dist-info/RECORD
